{
  "key": "plugin_content_manager_configuration_content_types::api::bph.bph",
  "value": {
    "uid": "api::bph.bph",
    "settings": {
      "bulkable": true,
      "filterable": true,
      "searchable": true,
      "pageSize": 10,
      "mainField": "name",
      "defaultSortBy": "name",
      "defaultSortOrder": "ASC"
    },
    "metadatas": {
      "id": {
        "edit": {},
        "list": {
          "label": "id",
          "searchable": true,
          "sortable": true
        }
      },
      "name": {
        "edit": {
          "label": "name",
          "description": "",
          "placeholder": "",
          "visible": true,
          "editable": true
        },
        "list": {
          "label": "name",
          "searchable": true,
          "sortable": true
        }
      },
      "profile_image": {
        "edit": {
          "label": "profile_image",
          "description": "",
          "placeholder": "",
          "visible": true,
          "editable": true
        },
        "list": {
          "label": "profile_image",
          "searchable": false,
          "sortable": false
        }
      },
      "jabatan": {
        "edit": {
          "label": "jabatan",
          "description": "",
          "placeholder": "",
          "visible": true,
          "editable": true
        },
        "list": {
          "label": "jabatan",
          "searchable": true,
          "sortable": true
        }
      },
      "urutan": {
        "edit": {
          "label": "urutan",
          "description": "",
          "placeholder": "",
          "visible": true,
          "editable": true
        },
        "list": {
          "label": "urutan",
          "searchable": true,
          "sortable": true
        }
      },
      "createdAt": {
        "edit": {
          "label": "createdAt",
          "description": "",
          "placeholder": "",
          "visible": false,
          "editable": true
        },
        "list": {
          "label": "createdAt",
          "searchable": true,
          "sortable": true
        }
      },
      "updatedAt": {
        "edit": {
          "label": "updatedAt",
          "description": "",
          "placeholder": "",
          "visible": false,
          "editable": true
        },
        "list": {
          "label": "updatedAt",
          "searchable": true,
          "sortable": true
        }
      }
    },
    "layouts": {
      "list": [
        "id",
        "name",
        "createdAt",
        "updatedAt"
      ],
      "edit": [
        [
          {
            "name": "name",
            "size": 6
          }
        ],
        [
          {
            "name": "profile_image",
            "size": 6
          },
          {
            "name": "jabatan",
            "size": 6
          }
        ],
        [
          {
            "name": "urutan",
            "size": 4
          }
        ]
      ]
    }
  },
  "type": "object",
  "environment": null,
  "tag": null
}